setup.cfg
setup.py
python_constantcontact/__init__.py
python_constantcontact/cc.py
python_constantcontact.egg-info/PKG-INFO
python_constantcontact.egg-info/SOURCES.txt
python_constantcontact.egg-info/dependency_links.txt
python_constantcontact.egg-info/requires.txt
python_constantcontact.egg-info/top_level.txt
python_constantcontact/django_constantcontact/__init__.py
python_constantcontact/django_constantcontact/admin.py
python_constantcontact/django_constantcontact/models.py
python_constantcontact/django_constantcontact/tests.py
python_constantcontact/django_constantcontact/management/__init__.py
python_constantcontact/django_constantcontact/management/commands/__init__.py
python_constantcontact/django_constantcontact/management/commands/constantcontactjobs.py