Metadata-Version: 1.1
Name: python-constantcontact
Version: 0.1
Summary: Constant contact lib for python, with stuff for Django too
Home-page: http://github.com/riltsken/python-constantcontact/tree/master
Author: Samuel Toriel
Author-email: samueltoriel@gmail.com
License: UNKNOWN
Platform: UNKNOWN
Classifier: Development Status :: 3 - Alpha
Classifier: Environment :: Web Environment
Classifier: Intended Audience :: Developers
Classifier: License :: OSI Approved :: BSD License
Classifier: Operating System :: OS Independent
Classifier: Programming Language :: Python
Classifier: Framework :: Django
